tcman/__init__.py
tcman/base.py
tcman/logger.py
tcman/roundrobin.py
tcman/path_builders/custom.py
tcman/path_builders/promiscuous.py
tcman-0.0.1.dist-info/LICENSE
tcman-0.0.1.dist-info/METADATA
tcman-0.0.1.dist-info/WHEEL
tcman-0.0.1.dist-info/top_level.txt
tcman-0.0.1.dist-info/RECORD
