Metadata-Version: 2.1
Name: tcman
Version: 0.0.1
Summary: Tor Circuits Manager
Home-page: https://github.com/amateur80lvl/tcman
Author: amateur80lvl
Author-email: amateur80lvl@gmail.com
Keywords: tor,onion,controller,asyncio
Classifier: Development Status :: 3 - Alpha
Classifier: Intended Audience :: Developers
Classifier: Programming Language :: Python
Classifier: Operating System :: OS Independent
Classifier: License :: OSI Approved :: GNU Lesser General Public License v3 (LGPLv3)
Classifier: Topic :: Security
Classifier: Topic :: Software Development :: Libraries :: Python Modules
License-File: LICENSE
Requires-Dist: mintc
